LICENSE
MANIFEST.in
README.md
setup.cfg
setup.py
caliper/__init__.py
caliper/logger.py
caliper/version.py
caliper.egg-info/PKG-INFO
caliper.egg-info/SOURCES.txt
caliper.egg-info/dependency_links.txt
caliper.egg-info/entry_points.txt
caliper.egg-info/not-zip-safe
caliper.egg-info/requires.txt
caliper.egg-info/top_level.txt
caliper/analysis/__init__.py
caliper/analysis/tasks.py
caliper/analysis/workers.py
caliper/client/__init__.py
caliper/client/analyze.py
caliper/client/extract.py
caliper/client/metrics.py
caliper/client/update.py
caliper/client/view.py
caliper/managers/__init__.py
caliper/managers/base.py
caliper/managers/dataverse.py
caliper/managers/git.py
caliper/managers/github.py
caliper/managers/pypi.py
caliper/metrics/__init__.py
caliper/metrics/base.py
caliper/metrics/extract.py
caliper/metrics/graphs.py
caliper/metrics/collection/__init__.py
caliper/metrics/collection/changedlines/metric.py
caliper/metrics/collection/changedlines/template.html
caliper/metrics/collection/functiondb/metric.py
caliper/metrics/collection/totalcounts/metric.py
caliper/utils/__init__.py
caliper/utils/command.py
caliper/utils/file.py
caliper/utils/prompt.py
tests/__init__.py
tests/test_analyze.py
tests/test_git.py
tests/test_managers.py
tests/test_metrics.py